medularis_django_utils-0.1.2.dist-info/pbr.json
medularis_django_utils-0.1.2.dist-info/metadata.json
medularis_django_utils-0.1.2.dist-info/WHEEL
medularis_django_utils-0.1.2.dist-info/RECORD
medularis_django_utils-0.1.2.dist-info/METADATA
medularis_django_utils-0.1.2.dist-info/top_level.txt
medularis_django_utils-0.1.2.dist-info/DESCRIPTION.rst
med_djutils/email.py
med_djutils/form_fields.py
med_djutils/views.py
med_djutils/test.py
med_djutils/context_processors.py
med_djutils/urls.py
med_djutils/log.py
med_djutils/model_fields.py
med_djutils/hex.py
med_djutils/models.py
med_djutils/__init__.py
med_djutils/normalization.py
tests/test_hex.py
tests/test_test.py
tests/test_email.py
tests/test_normalization.py
tests/__init__.py
tests/test_urls.py
