Metadata-Version: 2.0
Name: medularis-django-utils
Version: 0.1.2
Summary: Medularis's open source utilities for use in Django projects
Home-page: https://github.com/medularis/medularis-django-utils
Author: German Larrain
Author-email: glarrain@users.noreply.github.com
License: 3-clause BSD
Platform: UNKNOWN
Classifier: Development Status :: 4 - Beta
Classifier: Environment :: Web Environment
Classifier: Intended Audience :: Developers
Classifier: License :: OSI Approved :: BSD License
Classifier: Natural Language :: English
Classifier: Operating System :: OS Independent
Classifier: Programming Language :: Python
Classifier: Programming Language :: Python :: 2.7
Classifier: Programming Language :: Python :: 3
Classifier: Programming Language :: Python :: 3.3
Classifier: Programming Language :: Python :: 3.4
Classifier: Framework :: Django
Requires-Dist: Django (>=1.6)
